elemeta/__init__.py
elemeta/common/abstract_metafeature_extractor.py
elemeta/common/abstract_pair_metafeature_extractor.py
elemeta/dataset/__init__.py
elemeta/dataset/assets/avengers_endgame_tweets.zip
elemeta/dataset/assets/imdb_reviews.zip
elemeta/dataset/assets/tweets_likes.zip
elemeta/dataset/dataset.py
elemeta/nlp/__init__.py
elemeta/nlp/extractors/__init__.py
elemeta/nlp/extractors/high_level/__init__.py
elemeta/nlp/extractors/high_level/acronym_count.py
elemeta/nlp/extractors/high_level/avg_word_length.py
elemeta/nlp/extractors/high_level/capital_letters_ratio.py
elemeta/nlp/extractors/high_level/date_count.py
elemeta/nlp/extractors/high_level/detect_language_langdetect.py
elemeta/nlp/extractors/high_level/email_count.py
elemeta/nlp/extractors/high_level/embedding.py
elemeta/nlp/extractors/high_level/emoji_count.py
elemeta/nlp/extractors/high_level/hashtag_count.py
elemeta/nlp/extractors/high_level/hinted_profanity_sentence_count.py
elemeta/nlp/extractors/high_level/hinted_profanity_words_count.py
elemeta/nlp/extractors/high_level/link_count.py
elemeta/nlp/extractors/high_level/mention_count.py
elemeta/nlp/extractors/high_level/must_appear_words_percentage.py
elemeta/nlp/extractors/high_level/ner_identifier.py
elemeta/nlp/extractors/high_level/number_count.py
elemeta/nlp/extractors/high_level/out_of_vocabulary_count.py
elemeta/nlp/extractors/high_level/pii_identify.py
elemeta/nlp/extractors/high_level/punctuation_count.py
elemeta/nlp/extractors/high_level/regex_match_count.py
elemeta/nlp/extractors/high_level/semantic_text_pair_similarity.py
elemeta/nlp/extractors/high_level/sentence_avg_length.py
elemeta/nlp/extractors/high_level/sentence_count.py
elemeta/nlp/extractors/high_level/sentiment_polarity.py
elemeta/nlp/extractors/high_level/sentiment_subjectivity.py
elemeta/nlp/extractors/high_level/special_chars_count.py
elemeta/nlp/extractors/high_level/stop_words_count.py
elemeta/nlp/extractors/high_level/syllable_count.py
elemeta-1.3.3.dist-info/LICENSE
elemeta-1.3.3.dist-info/METADATA
elemeta-1.3.3.dist-info/WHEEL
elemeta-1.3.3.dist-info/RECORD
