Metadata-Version: 2.1
Name: elemeta
Version: 1.3.3
Summary: Metafeature Extraction for Unstructured Data
Home-page: https://docs.elemeta.ai
License: MIT
Author: Lior Durahly
Author-email: lior.durahly@superwise.ai
Requires-Python: >=3.8,<4.0.0
Classifier: License :: OSI Approved :: MIT License
Classifier: Programming Language :: Python :: 3
Classifier: Programming Language :: Python :: 3.8
Classifier: Programming Language :: Python :: 3.9
Classifier: Programming Language :: Python :: 3.10
Classifier: Programming Language :: Python :: 3.11
Classifier: Programming Language :: Python :: 3.12
Classifier: Programming Language :: Python :: 3.13
Requires-Dist: better-profanity (>=0.7,<0.8)
Requires-Dist: datefinder (>=0.7,<0.8)
Requires-Dist: emoji (>=2.2,<3.0)
Requires-Dist: langdetect (>=1.0,<2.0)
Requires-Dist: nltk (>=3.9,<4.0)
Requires-Dist: numpy (>=1.22,<2.0)
Requires-Dist: pandas (>=1.1,<2.0)
Requires-Dist: presidio-analyzer (>=2.2.33,<3.0.0)
Requires-Dist: profanity-check (>=1.0,<2.0)
Requires-Dist: pydantic (>=2.3.0,<3.0.0)
Requires-Dist: sentence-transformers (>=2.2.2,<3.0.0)
Requires-Dist: textblob (>=0.17,<0.18)
Requires-Dist: textstat (>=0.7,<0.8)
Requires-Dist: torch (>=2.0.1,<3.0.0)
Requires-Dist: transformers (>=4.36.0,<5.0.0)
Requires-Dist: vadersentiment (>=3.3,<4.0)
Project-URL: Documentation, https://docs.elemeta.ai
Project-URL: Repository, https://github.com/superwise-ai/elemeta
